melo/DSSP.py
melo/__init__.py
melo/core.py
melo/muliti_chain_score.py
melo/sst_paper.py
melo/dssp/__init__.py
melo/dssp/mkdssp
melopro-0.1.2.dist-info/METADATA
melopro-0.1.2.dist-info/WHEEL
melopro-0.1.2.dist-info/entry_points.txt
melopro-0.1.2.dist-info/top_level.txt
melopro-0.1.2.dist-info/RECORD
