Metadata-Version: 2.1
Name: melopro
Version: 0.1.2
Summary: A tool for protein structure analysis using DSSP.
Home-page: https://github.com/procom-ai/MELO
Author: Your Name
Author-email: your.email@example.com
Classifier: Programming Language :: Python :: 3
Classifier: License :: OSI Approved :: MIT License
Classifier: Operating System :: OS Independent
Requires-Python: >=3.7
Requires-Dist: pandas
Requires-Dist: matplotlib
Requires-Dist: biopython
